datamatch/__init__.py
datamatch/filters.py
datamatch/indices.py
datamatch/matchers.py
datamatch/pairers.py
datamatch/scorers.py
datamatch/similarities.py
datamatch/test_filters.py
datamatch/test_indices.py
datamatch/test_matchers.py
datamatch/test_pairers.py
datamatch/test_scorers.py
datamatch/test_similarities.py
datamatch/test_variators.py
datamatch/variators.py
datamatch-0.1.15.dist-info/LICENSE
datamatch-0.1.15.dist-info/METADATA
datamatch-0.1.15.dist-info/WHEEL
datamatch-0.1.15.dist-info/top_level.txt
datamatch-0.1.15.dist-info/RECORD
