Metadata-Version: 2.1
Name: datamatch
Version: 0.1.15
Summary: Data matching utilities
Home-page: https://github.com/pckhoi/datamatch
Author: Khoi Pham
Author-email: pckhoi@gmail.com
License: UNKNOWN
Project-URL: Bug Tracker, https://github.com/pckhoi/datamatch/issues
Platform: UNKNOWN
Classifier: Programming Language :: Python :: 3
Classifier: License :: OSI Approved :: MIT License
Classifier: Operating System :: OS Independent
Requires-Python: >=3.9
License-File: LICENSE
Requires-Dist: numpy (>=1.18)
Requires-Dist: pandas (>=1.2)
Requires-Dist: python-Levenshtein (>=0.12)
Requires-Dist: Unidecode (>=1.1)
Requires-Dist: tqdm (>=4.61.1)
